{
  "generate_infos": [
    {
      "mode": 1,
      "level": 1,
      "generateCount": 5,
      "minAppearDegree": -45.0,
      "maxAppearDegree": 45.0,
      "minScale": 1.5,
      "maxScale": 3.0,
      "minSpeed": 15.0,
      "maxSpeed": 30.0,
      "addSpeed": 0.02,
      "minShakeWidthX": -5.0,
      "maxShakeWidthX": 5.0,
      "minShakeWidthY": -6.5,
      "maxShakeWidthY": 6.5,
      "shakeWidthYCount": 3,
      "minWaitTime": 6.0,
      "maxWaitTime": 8.5,
      "appearEachCount": 2
    },
    {
      "mode": 1,
      "level": 2,
      "generateCount": 15,
      "minAppearDegree": -60.0,
      "maxAppearDegree": 60.0,
      "minScale": 1.0,
      "maxScale": 3.0,
      "minSpeed": 25.0,
      "maxSpeed": 45.0,
      "addSpeed": 0.02,
      "minShakeWidthX": -7.0,
      "maxShakeWidthX": 7.0,
      "minShakeWidthY": -8.5,
      "maxShakeWidthY": 8.5,
      "shakeWidthYCount": 3,
      "minWaitTime": 4.0,
      "maxWaitTime": 5.5,
      "appearEachCount": 3
    },
    {
      "mode": 1,
      "level": 3,
      "generateCount": 30,
      "minAppearDegree": -75.0,
      "maxAppearDegree": 75.0,
      "minScale": 0.8,
      "maxScale": 3.0,
      "minSpeed": 25.0,
      "maxSpeed": 45.0,
      "addSpeed": 0.03,
      "minShakeWidthX": -8.0,
      "maxShakeWidthX": 8.0,
      "minShakeWidthY": -9.0,
      "maxShakeWidthY": 9.0,
      "shakeWidthYCount": 3,
      "minWaitTime": 4.5,
      "maxWaitTime": 6.0,
      "appearEachCount": 5
    },
    {
      "mode": 2,
      "level": 1,
      "generateCount": 10,
      "minAppearDegree": -60.0,
      "maxAppearDegree": 60.0,
      "minScale": 1.5,
      "maxScale": 3.0,
      "minSpeed": 25.0,
      "maxSpeed": 45.0,
      "addSpeed": 0.02,
      "minShakeWidthX": -7.0,
      "maxShakeWidthX": 7.0,
      "minShakeWidthY": -8.0,
      "maxShakeWidthY": 8.0,
      "shakeWidthYCount": 3,
      "minWaitTime": 4.0,
      "maxWaitTime": 5.5,
      "appearEachCount": 3
    },
    {
      "mode": 2,
      "level": 2,
      "generateCount": 10,
      "minAppearDegree": -60.0,
      "maxAppearDegree": 60.0,
      "minScale": 1.2,
      "maxScale": 3.0,
      "minSpeed": 25.0,
      "maxSpeed": 45.0,
      "addSpeed": 0.02,
      "minShakeWidthX": -7.0,
      "maxShakeWidthX": 7.0,
      "minShakeWidthY": -8.0,
      "maxShakeWidthY": 8.0,
      "shakeWidthYCount": 3,
      "minWaitTime": 4.0,
      "maxWaitTime": 5.5,
      "appearEachCount": 4
    },
    {
      "mode": 2,
      "level": 3,
      "generateCount": 10,
      "minAppearDegree": -60.0,
      "maxAppearDegree": 60.0,
      "minScale": 1.2,
      "maxScale": 3.0,
      "minSpeed": 25.0,
      "maxSpeed": 45.0,
      "addSpeed": 0.02,
      "minShakeWidthX": -7.5,
      "maxShakeWidthX": 7.5,
      "minShakeWidthY": -8.5,
      "maxShakeWidthY": 8.5,
      "shakeWidthYCount": 3,
      "minWaitTime": 4.0,
      "maxWaitTime": 5.5,
      "appearEachCount": 5
    },
    {
      "mode": 2,
      "level": 4,
      "generateCount": 20,
      "minAppearDegree": -60.0,
      "maxAppearDegree": 60.0,
      "minScale": 1.0,
      "maxScale": 3.0,
      "minSpeed": 25.0,
      "maxSpeed": 45.0,
      "addSpeed": 0.02,
      "minShakeWidthX": -7.5,
      "maxShakeWidthX": 7.5,
      "minShakeWidthY": -8.5,
      "maxShakeWidthY": 8.5,
      "shakeWidthYCount": 3,
      "minWaitTime": 3.5,
      "maxWaitTime": 5.0,
      "appearEachCount": 5
    },
    {
      "mode": 2,
      "level": 5,
      "generateCount": 20,
      "minAppearDegree": -60.0,
      "maxAppearDegree": 60.0,
      "minScale": 1.0,
      "maxScale": 3.0,
      "minSpeed": 25.0,
      "maxSpeed": 50.0,
      "addSpeed": 0.02,
      "minShakeWidthX": -8.0,
      "maxShakeWidthX": 8.0,
      "minShakeWidthY": -9.0,
      "maxShakeWidthY": 9.0,
      "shakeWidthYCount": 3,
      "minWaitTime": 3.5,
      "maxWaitTime": 5.0,
      "appearEachCount": 5
    },
    {
      "mode": 2,
      "level": 6,
      "generateCount": 30,
      "minAppearDegree": -60.0,
      "maxAppearDegree": 60.0,
      "minScale": 0.8,
      "maxScale": 3.0,
      "minSpeed": 25.0,
      "maxSpeed": 50.0,
      "addSpeed": 0.02,
      "minShakeWidthX": -8.5,
      "maxShakeWidthX": 8.5,
      "minShakeWidthY": -9.0,
      "maxShakeWidthY": 9.0,
      "shakeWidthYCount": 3,
      "minWaitTime": 3.5,
      "maxWaitTime": 5.0,
      "appearEachCount": 7
    }
  ]
}